andvaranaut/__init__.py
andvaranaut/core.py
andvaranaut/gpmcmc.py
andvaranaut/lhc.py
andvaranaut/transform.py
andvaranaut-1.0.0.dist-info/LICENSE
andvaranaut-1.0.0.dist-info/WHEEL
andvaranaut-1.0.0.dist-info/METADATA
andvaranaut-1.0.0.dist-info/RECORD
