Metadata-Version: 2.1
Name: andvaranaut
Version: 1.0.0
Summary: Predictive modelling and UQ suite.
Author-email: Andrew Angus <andrewangus27@gmail.com>
Requires-Python: >=3.8
Requires-Dist: pymc <= 5.9.2
Requires-Dist: numpy
Requires-Dist: scipy
Requires-Dist: dask
Requires-Dist: distributed
Requires-Dist: scikit-learn
Requires-Dist: seaborn
Requires-Dist: cloudpickle
Requires-Dist: netCDF4
Requires-Dist: tqdm
Project-URL: Repository, https://github.com/andrew-angus/andvaranaut.git
